unique/__init__.py
unique/pipeline.py
unique/error_models/__init__.py
unique/error_models/base.py
unique/error_models/models/LASSO.py
unique/error_models/models/random_forest_regressor.py
unique/evaluation/__init__.py
unique/evaluation/base.py
unique/evaluation/evaluation_metrics.py
unique/evaluation/evaluation_plots.py
unique/input_type/__init__.py
unique/input_type/base.py
unique/uncertainty/__init__.py
unique/uncertainty/base.py
unique/uncertainty/data_based/__init__.py
unique/uncertainty/data_based/distance_to_training.py
unique/uncertainty/data_based/kernel_density.py
unique/uncertainty/model_based/__init__.py
unique/uncertainty/model_based/ensemble_variance.py
unique/uncertainty/model_based/probability.py
unique/uq_metric_factory/__init__.py
unique/uq_metric_factory/base.py
unique/uq_metric_factory/combinations/__init__.py
unique/uq_metric_factory/combinations/diffknn.py
unique/uq_metric_factory/combinations/sum_of_variances.py
unique/uq_metric_factory/preprocessing/__init__.py
unique/uq_metric_factory/preprocessing/distance_to_variance.py
unique/utils/__init__.py
unique/utils/error_model_utils.py
unique/utils/evaluation_utils.py
unique/utils/inference_utils.py
unique/utils/uncertainty_utils.py
unique_uncertainty-0.2.2.dist-info/LICENSE.md
unique_uncertainty-0.2.2.dist-info/WHEEL
unique_uncertainty-0.2.2.dist-info/METADATA
unique_uncertainty-0.2.2.dist-info/RECORD
