Metadata-Version: 2.1
Name: unique-uncertainty
Version: 0.2.2
Summary: UNIQUE is a Python package for benchmarking uncertainty estimation and quantification methods for Machine Learning models predictions.
Author: Raquel Rodriguez-Perez, Jessica Lanini, Minh Tam Davide Huynh, Gaetano Scebba
Requires-Python: >=3.8,<=3.12.1
Classifier: Development Status :: 4 - Beta
Classifier: Intended Audience :: Developers
Classifier: Intended Audience :: Education
Classifier: Intended Audience :: Science/Research
Classifier: License :: OSI Approved :: BSD License
Classifier: Programming Language :: Python
Classifier: Programming Language :: Python :: 3.8
Classifier: Programming Language :: Python :: 3.9
Classifier: Programming Language :: Python :: 3.10
Classifier: Programming Language :: Python :: 3.11
Classifier: Programming Language :: Python :: 3.12
Classifier: Programming Language :: Python :: 3
Classifier: Programming Language :: Python :: 3 :: Only
Classifier: Topic :: Scientific/Engineering
Classifier: Topic :: Scientific/Engineering :: Mathematics
Classifier: Topic :: Scientific/Engineering :: Artificial Intelligence
Classifier: Topic :: Software Development
Classifier: Topic :: Software Development :: Libraries
Classifier: Topic :: Software Development :: Libraries :: Python Modules
Requires-Dist: colorcet>=3.0,<=3.0.1
Requires-Dist: ipykernel>=6.29,<=6.29.2
Requires-Dist: jinja2>=3.1,<=3.1.3
Requires-Dist: matplotlib>=3.6,<=3.8.2
Requires-Dist: numpy>=1.19,<=1.26.4
Requires-Dist: pandas>=2.0,<=2.2.0
Requires-Dist: pyarrow<=16.1.0
Requires-Dist: pyyaml>=6.0,<=6.0.1
Requires-Dist: rdkit==2023.09.1
Requires-Dist: ruamel.yaml>=0.17
Requires-Dist: scikit-learn>=1.3,<=1.4.0
Requires-Dist: scipy>=1.10,<=1.12.0
Requires-Dist: seaborn>=0.13,<=0.13.2
Requires-Dist: shapely>=2.0,<=2.0.2
Requires-Dist: statsmodels>=0.13.3,<=0.14.2
Requires-Dist: tqdm>=4.65,<=4.66.2
Requires-Dist: black==24.2.0 ; extra == "dev"
Requires-Dist: flit>=3.2,<4 ; extra == "dev"
Requires-Dist: genbadge>=1.1.1 ; extra == "dev"
Requires-Dist: isort==5.13.2 ; extra == "dev"
Requires-Dist: linkify-it-py==2.0.3 ; extra == "dev"
Requires-Dist: myst-nb>=1.1.0 ; extra == "dev"
Requires-Dist: myst-parser>=3,<=4 ; extra == "dev"
Requires-Dist: nbconvert==7.16.0 ; extra == "dev"
Requires-Dist: pre-commit==3.6.2 ; extra == "dev"
Requires-Dist: pytest>=7.2 ; extra == "dev"
Requires-Dist: pytest-cov>=4.1 ; extra == "dev"
Requires-Dist: sphinx>=7.3.7 ; extra == "dev"
Requires-Dist: sphinx-autoapi>=3.1.1 ; extra == "dev"
Requires-Dist: sphinx-autodoc2>=0.5.0 ; extra == "dev"
Requires-Dist: sphinx-book-theme>=1.1.2 ; extra == "dev"
Requires-Dist: sphinx-copybutton==0.5.2 ; extra == "dev"
Requires-Dist: sphinx-design>=0.5,<0.7 ; extra == "dev"
Requires-Dist: tox>=3.27,<=4.12.1 ; extra == "dev"
Requires-Dist: tox-conda>=0.10,<=0.10.2 ; extra == "dev"
Project-URL: Documentation, https://opensource.nibr.com/UNIQUE
Project-URL: Repository, https://github.com/Novartis/UNIQUE
Provides-Extra: dev
